1joepie_prank-0.4.0.dist-info/licenses/LICENSE
joepie_tools/__init__.py
joepie_tools/cli.py
joepie_tools/hackerprank/__init__.py
joepie_tools/hackerprank/bsod.py
joepie_tools/hackerprank/fake_screens.py
joepie_tools/hackerprank/fake_terminal.py
joepie_tools/hackerprank/file_dump.py
joepie_tools/hackerprank/matrix_screen.py
joepie_tools/hackerprank/popup.py
joepie_tools/hackerprank/random_popups.py
joepie_tools/hackerprank/runner.py
joepie_tools/hackerprank/sound.py
joepie_tools/hackerprank/update_screen.py
joepie_tools/hackerprank/virus_scan.py
1joepie_prank-0.4.0.dist-info/METADATA
1joepie_prank-0.4.0.dist-info/WHEEL
1joepie_prank-0.4.0.dist-info/top_level.txt
1joepie_prank-0.4.0.dist-info/RECORD
