Metadata-Version: 2.4
Name: 1joepie_prank
Version: 0.4.0
Summary: Joepie's prank tools: safe fake hacker GUIs, terminals and effects (more realistic)
Author: Noah
Author-email: Noah <noah@example.com>
License-Expression: MIT
Keywords: prank,gui,fun,fake,toy
License-File: LICENSE
Dynamic: author
Dynamic: license-file
